robust_json/__init__.py
robust_json/__internal_utils.py
robust_json/errors.py
robust_json/file.py
robust_json/object.py
robust_json/ext/__init__.py
robust_json/ext/filter_json_array.py
robust_json/ext/get_item_index.py
robust_json/ext/reverse_array.py
robust_json-1.2.7.dist-info/LICENSE
robust_json-1.2.7.dist-info/METADATA
robust_json-1.2.7.dist-info/WHEEL
robust_json-1.2.7.dist-info/top_level.txt
robust_json-1.2.7.dist-info/RECORD
