Metadata-Version: 2.1
Name: robust-json
Version: 1.2.7
Summary: Robust and easy-to-use framework for working with JSON
Home-page: https://github.com/NickolaiBeloguzov/robust-json
Author: Nickolai Beloguzov
Author-email: nickolai.beloguzov@gmail.com
License: Apache 2.0
Platform: UNKNOWN
Classifier: License :: OSI Approved :: Apache Software License
Classifier: Programming Language :: Python :: 3
Classifier: Programming Language :: Python :: 3.8
Classifier: Programming Language :: Python :: 3.9
Classifier: Operating System :: OS Independent
Requires-Python: >=3.8
Requires-Dist: jsonpath-ng
Requires-Dist: pathlib2
